pam/__init__.py
pam/revbits_ansible/__init__.py
pam/revbits_ansible/server.py
revbits_ansible-1.3.1.dist-info/LICENSE
revbits_ansible-1.3.1.dist-info/WHEEL
revbits_ansible-1.3.1.dist-info/METADATA
revbits_ansible-1.3.1.dist-info/RECORD
