Metadata-Version: 2.1
Name: revbits_ansible
Version: 1.3.1
Summary: The PAM Secret Server Python SDK
Author: RevBits
Author-email: info@revbits.com
Requires-Python: >=3.6
Classifier: License :: OSI Approved :: Apache Software License
Classifier: Operating System :: OS Independent
Classifier: Programming Language :: Python :: 3.6
Classifier: Programming Language :: Python :: 3.7
Classifier: Programming Language :: Python :: 3.8
Classifier: Programming Language :: Python :: 3.9
Requires-Dist: requests >= 2.12.5
Requires-Dist: aes-everywhere >= 1.2.10
